codedjinn/__init__.py
codedjinn/config.py
codedjinn/llmfactory.py
codedjinn/main.py
codedjinn/parser.py
codedjinn/parser_config.py
codedjinn/utils.py
codedjinn/core/__init__.py
codedjinn/core/command_executor.py
codedjinn/core/djinn.py
codedjinn/core/llm_cache.py
codedjinn/core/prompt_builder.py
codedjinn/core/response_parser.py
codedjinn/modes/__init__.py
codedjinn/modes/execution_mode.py
codedjinn/modes/question_mode.py
codedjinn/providers/__init__.py
codedjinn/providers/parameter_manager.py
tests/__init__.py
tests/test_command_executor.py
tests/test_config.py
tests/test_prompt_builder.py
tests/test_response_parser.py
tests/test_utils.py
code_djinn-0.2.2.dist-info/METADATA
code_djinn-0.2.2.dist-info/WHEEL
code_djinn-0.2.2.dist-info/entry_points.txt
code_djinn-0.2.2.dist-info/top_level.txt
code_djinn-0.2.2.dist-info/RECORD
