Metadata-Version: 2.4
Name: code_djinn
Version: 0.2.2
Summary: High-performance CLI assistant for generating shell commands using LLM models
Author: phisanti
Author-email: phisanti <tisalon@outlook.com>
License: MIT
Requires-Python: >=3.10
Requires-Dist: langchain-community>=0.3.20
Requires-Dist: langchain-mistralai>=0.2.9
Requires-Dist: langchain-google-genai>=2.1.1
Requires-Dist: python-dotenv>=1.0.0
Dynamic: author
Dynamic: requires-python
